<?xml version="1.0" encoding="UTF-8"?>
<trafficDefinition
        xmlns="https://github.com/Engin1980/J-ATC-Simulator/traffic">
  <meta>
    <title>Generic traffic low</title>
    <author>Marek Vajgl</author>
    <description>
      Generic low traffic defines very low traffic with morning and afternoon low peaks (up to 10 movements/hour).
    </description>
  </meta>
  <genericTraffic defaultProbabilityOfDeparture=".5"
                  defaultProbabilityOfGeneralAviation=".1"
                  useExtendedCallsigns="true">
    <movements>
      <movementsForHour count="0"/>
      <movementsForHour count="0"/>
      <movementsForHour count="0"/>
      <movementsForHour count="0"/>
      <movementsForHour count="0"/>
      <movementsForHour count="3" departureProbability="1" probabilityOfGeneralAviation="1"/>
      <movementsForHour count="5" departureProbability=".8" probabilityOfGeneralAviation=".8"/>
      <movementsForHour count="4" departureProbability="0.8"/>
      <movementsForHour count="8" departureProbability="0.8"/>
      <movementsForHour count="3" departureProbability="0.6"/>
      <movementsForHour count="4" departureProbability="0.3"/>
      <movementsForHour count="7" departureProbability="0.5"/>
      <movementsForHour count="8" departureProbability="0.2"/>
      <movementsForHour count="4" departureProbability="0.1"/>
      <movementsForHour count="2" departureProbability="0.3"/>
      <movementsForHour count="5" departureProbability="0.5"/>
      <movementsForHour count="10" departureProbability="0.4"/>
      <movementsForHour count="6" departureProbability="0.7"/>
      <movementsForHour count="3" departureProbability="0.7"/>
      <movementsForHour count="2" departureProbability="0.8"/>
      <movementsForHour count="9" departureProbability="0.6"/>
      <movementsForHour count="5" departureProbability="0.8" probabilityOfGeneralAviation=".4"/>
      <movementsForHour count="2" departureProbability="0.9"/>
      <movementsForHour count="1" departureProbability="1"/>
    </movements>
    <companies>
      <item weight="5">CSA</item>
      <item>RYR</item>
      <item>EZY</item>
      <item>DHL</item>
      <item>BAW</item>
      <item>AUA</item>
    </companies>
    <countryCodes>
      <item>DE</item>
      <item>AT</item>
      <item>OK</item>
      <item>OM</item>
      <item>G</item>
      <item>AU</item>
    </countryCodes>
  </genericTraffic>
</trafficDefinition>